spiderutil/__init__.py
spiderutil/exceptions.py
spiderutil/log.py
spiderutil/media.py
spiderutil/typing.py
spiderutil/connector/__init__.py
spiderutil/connector/base.py
spiderutil/connector/local.py
spiderutil/connector/mongo.py
spiderutil/connector/redis.py
spiderutil/network/__init__.py
spiderutil/network/api.py
spiderutil/network/session.py
spiderutil/network/useragent.py
spiderutil/path/__init__.py
spiderutil/path/base.py
spiderutil/path/simple.py
spiderutil/path/user.py
spiderutil/structure/__init__.py
spiderutil/structure/dict.py
spiderutil/util/structure.py
spiderutil-0.1.8.dist-info/LICENSE.txt
spiderutil-0.1.8.dist-info/METADATA
spiderutil-0.1.8.dist-info/WHEEL
spiderutil-0.1.8.dist-info/top_level.txt
spiderutil-0.1.8.dist-info/RECORD
