Metadata-Version: 2.1
Name: spiderutil
Version: 0.1.8
Summary: Utilities for spider.
Home-page: https://github.com/Thesharing/spider-utility
Author: Thesharing
Author-email: 
License: MIT
Platform: UNKNOWN
Classifier: Development Status :: 4 - Beta
Classifier: Environment :: Console
Classifier: Intended Audience :: Developers
Classifier: Operating System :: OS Independent
Classifier: Programming Language :: Python
Classifier: Topic :: Utilities
Requires-Python: >=2.7, !=3.0.*, !=3.1.*, !=3.2.*, <4
Requires-Dist: redis (>=3.3.0)
Requires-Dist: pymongo (>=3.8.0)
Requires-Dist: requests (>=2.20.0)
